MANIFEST.in
README.rst
setup.cfg
setup.py
stump/__init__.py
stump/stump.py
stump.egg-info/PKG-INFO
stump.egg-info/SOURCES.txt
stump.egg-info/dependency_links.txt
stump.egg-info/not-zip-safe
stump.egg-info/top_level.txt