Metadata-Version: 1.0
Name: stump
Version: 0.12
Summary: Logs program flow with decorators
Home-page: http://github.com/EricCrosson/stump
Author: Eric Crosson
Author-email: eric.s.crosson@utexas.edu
License: MIT
Platform: UNKNOWN
